hyp3_sdk/__init__.py
hyp3_sdk/exceptions.py
hyp3_sdk/hyp3.py
hyp3_sdk/jobs.py
hyp3_sdk/util.py
hyp3_sdk-7.7.6.dist-info/licenses/LICENSE
hyp3_sdk-7.7.6.dist-info/METADATA
hyp3_sdk-7.7.6.dist-info/WHEEL
hyp3_sdk-7.7.6.dist-info/top_level.txt
hyp3_sdk-7.7.6.dist-info/RECORD
