Metadata-Version: 2.4
Name: hyp3_sdk
Version: 7.7.6
Summary: A python wrapper around the HyP3 API
Author-email: ASF APD/Tools Team <uaf-asf-apd@alaska.edu>
License: BSD-3-Clause
Project-URL: Homepage, https://github.com/ASFHyP3/hyp3-sdk
Project-URL: Bug Tracker, https://github.com/ASFHyP3/hyp3-sdk/issues
Classifier: Intended Audience :: Science/Research
Classifier: License :: OSI Approved :: BSD License
Classifier: Natural Language :: English
Classifier: Operating System :: OS Independent
Classifier: Programming Language :: Python :: 3
Classifier: Programming Language :: Python :: 3.10
Classifier: Programming Language :: Python :: 3.11
Classifier: Programming Language :: Python :: 3.12
Requires-Python: >=3.10
License-File: LICENSE
Requires-Dist: python-dateutil
Requires-Dist: requests
Requires-Dist: urllib3
Requires-Dist: tqdm
Provides-Extra: develop
Requires-Dist: pytest; extra == "develop"
Requires-Dist: pytest-cov; extra == "develop"
Requires-Dist: responses; extra == "develop"
Dynamic: license-file
